gulagcleaner/__init__.py
gulagcleaner/_lib.cp311-win_amd64.pyd
gulagcleaner/clean.py
gulagcleaner/command_line.py
gulagcleaner/decrypt.py
gulagcleaner/metadata.py
gulagcleaner-4.dist-info/LICENSE
gulagcleaner-4.dist-info/METADATA
gulagcleaner-4.dist-info/WHEEL
gulagcleaner-4.dist-info/entry_points.txt
gulagcleaner-4.dist-info/top_level.txt
gulagcleaner-4.dist-info/RECORD
