Metadata-Version: 2.1
Name: gulagcleaner
Version: 4
Summary: Ad removal tool for PDFs.
Author-email: YM162 <david.fontaneda@YM162.dev>
License: GNU GENERAL PUBLIC LICENSE
Project-URL: homepage, https://github.com/YM162/gulag-cleaner-cli
Project-URL: repository, https://github.com/YM162/gulag-cleaner-cli.git
Project-URL: issues, https://github.com/YM162/gulag-cleaner-cli/issues
Keywords: wuolah,studocu,pdf,stucleaner,gulagcleaner
Classifier: Programming Language :: Python :: 3
Classifier: License :: OSI Approved :: MIT License
Classifier: Operating System :: OS Independent
License-File: LICENSE
Requires-Dist: pikepdf>=8.10.1
Requires-Dist: pdfminer.six>=20220524
